[
    {
        "lat": 35.154758,
        "lng": 126.883394,
        "score": 0
    },
    {
        "lat": 35.154758,
        "lng": 126.883894,
        "score": 0
    },
    {
        "lat": 35.154758,
        "lng": 126.884394,
        "score": 0
    },
    {
        "lat": 35.154758,
        "lng": 126.884894,
        "score": 4
    },
    {
        "lat": 35.155258,
        "lng": 126.883394,
        "score": 0
    },
    {
        "lat": 35.155258,
        "lng": 126.883894,
        "score": 2
    },
    {
        "lat": 35.155258,
        "lng": 126.884394,
        "score": 2
    },
    {
        "lat": 35.155258,
        "lng": 126.884894,
        "score": 0
    },
    {
        "lat": 35.155758,
        "lng": 126.883394,
        "score": 0
    },
    {
        "lat": 35.155758,
        "lng": 126.883894,
        "score": 0
    },
    {
        "lat": 35.155758,
        "lng": 126.884394,
        "score": 2
    },
    {
        "lat": 35.155758,
        "lng": 126.884894,
        "score": 0
    },
    {
        "lat": 35.156258,
        "lng": 126.883394,
        "score": 0
    },
    {
        "lat": 35.156258,
        "lng": 126.883894,
        "score": 0
    },
    {
        "lat": 35.156258,
        "lng": 126.884394,
        "score": 0
    },
    {
        "lat": 35.156258,
        "lng": 126.884894,
        "score": 0
    }
]