[
    {
        "lat": 35.130258000000005,
        "lng": 126.905894,
        "score": 4
    },
    {
        "lat": 35.130258000000005,
        "lng": 126.906394,
        "score": 6
    },
    {
        "lat": 35.130258000000005,
        "lng": 126.90689400000001,
        "score": 6
    },
    {
        "lat": 35.130258000000005,
        "lng": 126.907394,
        "score": 0
    },
    {
        "lat": 35.130258000000005,
        "lng": 126.907894,
        "score": 0
    },
    {
        "lat": 35.130758,
        "lng": 126.905894,
        "score": 0
    },
    {
        "lat": 35.130758,
        "lng": 126.906394,
        "score": 0
    },
    {
        "lat": 35.130758,
        "lng": 126.90689400000001,
        "score": 0
    },
    {
        "lat": 35.130758,
        "lng": 126.907394,
        "score": 0
    },
    {
        "lat": 35.130758,
        "lng": 126.907894,
        "score": 0
    },
    {
        "lat": 35.131258,
        "lng": 126.905894,
        "score": 0
    },
    {
        "lat": 35.131258,
        "lng": 126.906394,
        "score": 0
    },
    {
        "lat": 35.131258,
        "lng": 126.90689400000001,
        "score": 0
    },
    {
        "lat": 35.131258,
        "lng": 126.907394,
        "score": 0
    },
    {
        "lat": 35.131258,
        "lng": 126.907894,
        "score": 0
    },
    {
        "lat": 35.131758000000005,
        "lng": 126.905894,
        "score": 0
    },
    {
        "lat": 35.131758000000005,
        "lng": 126.906394,
        "score": 0
    },
    {
        "lat": 35.131758000000005,
        "lng": 126.90689400000001,
        "score": 0
    },
    {
        "lat": 35.131758000000005,
        "lng": 126.907394,
        "score": 4
    },
    {
        "lat": 35.131758000000005,
        "lng": 126.907894,
        "score": 4
    }
]