[
    {
        "lat": 35.150258,
        "lng": 126.726394,
        "score": 0
    },
    {
        "lat": 35.150258,
        "lng": 126.726894,
        "score": 0
    },
    {
        "lat": 35.150258,
        "lng": 126.727394,
        "score": 0
    },
    {
        "lat": 35.150258,
        "lng": 126.727894,
        "score": 0
    },
    {
        "lat": 35.150758,
        "lng": 126.726394,
        "score": 0
    },
    {
        "lat": 35.150758,
        "lng": 126.726894,
        "score": 0
    },
    {
        "lat": 35.150758,
        "lng": 126.727394,
        "score": 0
    },
    {
        "lat": 35.150758,
        "lng": 126.727894,
        "score": 0
    },
    {
        "lat": 35.151258,
        "lng": 126.726394,
        "score": 0
    },
    {
        "lat": 35.151258,
        "lng": 126.726894,
        "score": 0
    },
    {
        "lat": 35.151258,
        "lng": 126.727394,
        "score": 0
    },
    {
        "lat": 35.151258,
        "lng": 126.727894,
        "score": 0
    },
    {
        "lat": 35.151758,
        "lng": 126.726394,
        "score": 0
    },
    {
        "lat": 35.151758,
        "lng": 126.726894,
        "score": 0
    },
    {
        "lat": 35.151758,
        "lng": 126.727394,
        "score": 0
    },
    {
        "lat": 35.151758,
        "lng": 126.727894,
        "score": 0
    }
]